metaml/__init__.py
metaml/exceptions.py
metaml/_util/__init__.py
metaml/_util/hf_callback.py
metaml/_util/log_config.yml
metaml/_util/logger.py
metaml/_util/typing.py
metaml/_util/utils.py
metaml/_util/target_transformers/__init__.py
metaml/_util/target_transformers/power_target_transformer.py
metaml/factory/__init__.py
metaml/factory/factory.py
metaml/factory/parameter_settings.py
metaml/factory/constraint_handling/__init__.py
metaml/factory/constraint_handling/combine_constrained_parameters.py
metaml/factory/constraint_handling/constraint_validation.py
metaml/meta_models/__init__.py
metaml/meta_models/meta_model.py
metaml/meta_models/metadata.py
metaml/meta_models/names.py
metaml/meta_models/parameters.py
metaml/meta_models/classifiers/__init__.py
metaml/meta_models/classifiers/meta_classifier.py
metaml/meta_models/classifiers/catboost/__init__.py
metaml/meta_models/classifiers/catboost/catboost_classifier.py
metaml/meta_models/classifiers/catboost/catboost/__init__.py
metaml/meta_models/classifiers/catboost/catboost/catboost_classifier.json
metaml/meta_models/classifiers/catboost/catboost/metadata.py
metaml/meta_models/classifiers/catboost/catboost/model.py
metaml/meta_models/classifiers/catboost/catboost/parameters.py
metaml/meta_models/classifiers/catboost/catboost/space/__init__.py
metaml/meta_models/classifiers/catboost/catboost/space/graph.py
metaml/meta_models/classifiers/catboost/catboost/space/nodes.py
metaml/meta_models/classifiers/huggingface/__init__.py
metaml/meta_models/classifiers/huggingface/huggingface_classifier.py
metaml/meta_models/classifiers/huggingface/nlp_sequence/__init__.py
metaml/meta_models/classifiers/huggingface/nlp_sequence/metadata.py
metaml/meta_models/classifiers/huggingface/nlp_sequence/model.py
metaml/meta_models/classifiers/huggingface/nlp_sequence/nlp_sequence_classifier.json
metaml/meta_models/classifiers/huggingface/nlp_sequence/parameters.py
metaml/meta_models/classifiers/huggingface/nlp_sequence/space/__init__.py
turintech_evoml_metaml-3.2.2.dist-info/LICENSE
turintech_evoml_metaml-3.2.2.dist-info/METADATA
turintech_evoml_metaml-3.2.2.dist-info/WHEEL
turintech_evoml_metaml-3.2.2.dist-info/top_level.txt
turintech_evoml_metaml-3.2.2.dist-info/RECORD
